app/__init__.py
app/calc.py
app/subpackage/__init__.py
demo_2-1.1.2.dist-info/.ipynb_checkpoints/SOURCES-checkpoint.txt
demo_2-1.1.2.dist-info/METADATA
demo_2-1.1.2.dist-info/WHEEL
demo_2-1.1.2.dist-info/top_level.txt
demo_2-1.1.2.dist-info/RECORD
