Metadata-Version: 2.1
Name: demo-2
Version: 1.1.2
Summary: demo_2
Home-page: https://itec-stash.fmr.com/projects/PR105104/repos/ap130681-am-svc-ordsen-ai-model-execution-service/browse
Author: Equity PM
Author-email: a600207@fmr.com
License: UNKNOWN
Platform: UNKNOWN
Classifier: Programming Language :: Python :: 3
Classifier: Operating System :: OS Independent
Requires-Dist: joblib (==0.13.2)
Requires-Dist: numpy (==1.15.4)
Requires-Dist: pandas (==0.24.1)
Requires-Dist: pylint
Requires-Dist: yapf
Requires-Dist: pytest
Requires-Dist: pytest-runner
